odoo/addons/server_environment_ir_config_parameter/README.rst
odoo/addons/server_environment_ir_config_parameter/__init__.py
odoo/addons/server_environment_ir_config_parameter/__manifest__.py
odoo/addons/server_environment_ir_config_parameter/i18n/de.po
odoo/addons/server_environment_ir_config_parameter/i18n/es.po
odoo/addons/server_environment_ir_config_parameter/i18n/it.po
odoo/addons/server_environment_ir_config_parameter/i18n/nl_NL.po
odoo/addons/server_environment_ir_config_parameter/i18n/ro.po
odoo/addons/server_environment_ir_config_parameter/i18n/server_environment_ir_config_parameter.pot
odoo/addons/server_environment_ir_config_parameter/models/__init__.py
odoo/addons/server_environment_ir_config_parameter/models/ir_config_parameter.py
odoo/addons/server_environment_ir_config_parameter/readme/CONFIGURE.rst
odoo/addons/server_environment_ir_config_parameter/readme/CONTRIBUTORS.rst
odoo/addons/server_environment_ir_config_parameter/readme/CREDITS.rst
odoo/addons/server_environment_ir_config_parameter/readme/DESCRIPTION.rst
odoo/addons/server_environment_ir_config_parameter/readme/USAGE.rst
odoo/addons/server_environment_ir_config_parameter/static/description/icon.png
odoo/addons/server_environment_ir_config_parameter/static/description/index.html
odoo/addons/server_environment_ir_config_parameter/tests/__init__.py
odoo/addons/server_environment_ir_config_parameter/tests/config_param_test.xml
odoo/addons/server_environment_ir_config_parameter/tests/test_server_environment_ircp.py
odoo/addons/server_environment_ir_config_parameter/views/view_ir_config_parameter.xml
odoo12_addon_server_environment_ir_config_parameter-12.0.1.0.1.dist-info/METADATA
odoo12_addon_server_environment_ir_config_parameter-12.0.1.0.1.dist-info/WHEEL
odoo12_addon_server_environment_ir_config_parameter-12.0.1.0.1.dist-info/top_level.txt
odoo12_addon_server_environment_ir_config_parameter-12.0.1.0.1.dist-info/RECORD
